crossout/CrossoutDB.py
crossout/CrossoutDBAPI.py
crossout/__init__.py
crossout/objects.py
crossout-1.0.0.dist-info/LICENSE
crossout-1.0.0.dist-info/METADATA
crossout-1.0.0.dist-info/WHEEL
crossout-1.0.0.dist-info/top_level.txt
crossout-1.0.0.dist-info/RECORD
