Metadata-Version: 2.1
Name: crossout
Version: 1.0.0
Summary: Python package using the API of CrossoutDB
Author: Z-WX
Project-URL: Repository, https://github.com/ZWerduex/crossout
Project-URL: Issues, https://github.com/ZWerduex/crossout/issues
Classifier: Development Status :: 3 - Alpha
Classifier: License :: OSI Approved :: GNU General Public License v3 (GPLv3)
Classifier: Natural Language :: English
Classifier: Operating System :: OS Independent
Classifier: Programming Language :: Python :: 3
Classifier: Topic :: Database :: Front-Ends
Classifier: Topic :: Games/Entertainment
Classifier: Topic :: Internet :: WWW/HTTP :: Dynamic Content
Classifier: Topic :: Software Development :: Libraries :: Python Modules
Classifier: Typing :: Typed
Requires-Python: >=3.10
License-File: LICENSE
Requires-Dist: requests (>=2.30.0)
Requires-Dist: urllib3 (>=2.0.2)
